TCI_tool/__init__.py
TCI_tool/catchment_tools.py
TCI_tool/definitions.py
TCI_tool/dem_tools.py
TCI_tool/logging_config.py
TCI_tool/main.py
TCI_tool/raster_tools.py
TCI_tool/sink_tools.py
tci_tool-0.0.3.dist-info/METADATA
tci_tool-0.0.3.dist-info/WHEEL
tci_tool-0.0.3.dist-info/licenses/LICENSE
tci_tool-0.0.3.dist-info/RECORD
